{
	"_version": "1.1.0",
	"resources": [
		{
			"name": ".theme",
			"size": 660,
			"theme": "sap_belize_hcw"
		},
		{
			"name": ".theming",
			"size": 93,
			"theme": "sap_belize_hcw"
		},
		{
			"name": "BrowserScrollbar.less",
			"size": 431,
			"designtime": true,
			"theme": "sap_belize_hcw"
		},
		{
			"name": "LocalBusyIndicator.less",
			"size": 567,
			"designtime": true,
			"theme": "sap_belize_hcw"
		},
		{
			"name": "Shadow.less",
			"size": 201,
			"designtime": true,
			"theme": "sap_belize_hcw"
		},
		{
			"name": "base.less",
			"size": 70267,
			"designtime": true,
			"theme": "sap_belize_hcw"
		},
		{
			"name": "css_variables.css",
			"size": 204763,
			"theme": "sap_belize_hcw"
		},
		{
			"name": "css_variables.less",
			"size": 228331,
			"designtime": true,
			"theme": "sap_belize_hcw"
		},
		{
			"name": "css_variables.source.less",
			"size": 227957,
			"designtime": true,
			"theme": "sap_belize_hcw"
		},
		{
			"name": "fonts/72-Bold-full.woff2",
			"size": 56684,
			"theme": "sap_belize_hcw"
		},
		{
			"name": "fonts/72-Bold.woff2",
			"size": 24336,
			"theme": "sap_belize_hcw"
		},
		{
			"name": "fonts/72-Light-full.woff2",
			"size": 57936,
			"theme": "sap_belize_hcw"
		},
		{
			"name": "fonts/72-Light.woff2",
			"size": 24936,
			"theme": "sap_belize_hcw"
		},
		{
			"name": "fonts/72-Regular-full.woff2",
			"size": 56160,
			"theme": "sap_belize_hcw"
		},
		{
			"name": "fonts/72-Regular.woff2",
			"size": 24396,
			"theme": "sap_belize_hcw"
		},
		{
			"name": "fonts/72Mono-Bold-full.woff2",
			"size": 51544,
			"theme": "sap_belize_hcw"
		},
		{
			"name": "fonts/72Mono-Bold.woff2",
			"size": 22044,
			"theme": "sap_belize_hcw"
		},
		{
			"name": "fonts/72Mono-Regular-full.woff2",
			"size": 50276,
			"theme": "sap_belize_hcw"
		},
		{
			"name": "fonts/72Mono-Regular.woff2",
			"size": 21800,
			"theme": "sap_belize_hcw"
		},
		{
			"name": "global.less",
			"size": 64420,
			"designtime": true,
			"theme": "sap_belize_hcw"
		},
		{
			"name": "library-RTL.css",
			"size": 125487,
			"theme": "sap_belize_hcw"
		},
		{
			"name": "library-parameters.json",
			"size": 73843,
			"theme": "sap_belize_hcw"
		},
		{
			"name": "library.css",
			"size": 125472,
			"theme": "sap_belize_hcw"
		},
		{
			"name": "library.less",
			"size": 8995,
			"designtime": true,
			"theme": "sap_belize_hcw"
		},
		{
			"name": "library.source.less",
			"size": 350,
			"designtime": true,
			"theme": "sap_belize_hcw"
		},
		{
			"name": "library_skeleton-RTL.css",
			"size": 27482,
			"theme": "sap_belize_hcw"
		},
		{
			"name": "library_skeleton.css",
			"size": 27468,
			"theme": "sap_belize_hcw"
		},
		{
			"name": "shared.less",
			"size": 7118,
			"designtime": true,
			"theme": "sap_belize_hcw"
		}
	]
}