{
	"_version": "1.1.0",
	"resources": [
		{
			"name": ".theming",
			"size": 94,
			"theme": "sap_fiori_3_hcb"
		},
		{
			"name": "AnchorBar.less",
			"size": 7089,
			"designtime": true,
			"theme": "sap_fiori_3_hcb"
		},
		{
			"name": "BreadCrumbs.less",
			"size": 617,
			"designtime": true,
			"theme": "sap_fiori_3_hcb"
		},
		{
			"name": "HierarchicalSelect.less",
			"size": 3946,
			"designtime": true,
			"theme": "sap_fiori_3_hcb"
		},
		{
			"name": "IconTabBar.less",
			"size": 388,
			"designtime": true,
			"theme": "sap_fiori_3_hcb"
		},
		{
			"name": "ObjectPageHeader.less",
			"size": 3739,
			"designtime": true,
			"theme": "sap_fiori_3_hcb"
		},
		{
			"name": "ObjectPageHeaderContent.less",
			"size": 3039,
			"designtime": true,
			"theme": "sap_fiori_3_hcb"
		},
		{
			"name": "ObjectPageLayout.less",
			"size": 2010,
			"designtime": true,
			"theme": "sap_fiori_3_hcb"
		},
		{
			"name": "ObjectPageSection.less",
			"size": 1636,
			"designtime": true,
			"theme": "sap_fiori_3_hcb"
		},
		{
			"name": "ObjectPageSubSection.less",
			"size": 1452,
			"designtime": true,
			"theme": "sap_fiori_3_hcb"
		},
		{
			"name": "css_variables.css",
			"size": 699,
			"theme": "sap_fiori_3_hcb"
		},
		{
			"name": "css_variables.less",
			"size": 114113,
			"designtime": true,
			"theme": "sap_fiori_3_hcb"
		},
		{
			"name": "css_variables.source.less",
			"size": 113743,
			"designtime": true,
			"theme": "sap_fiori_3_hcb"
		},
		{
			"name": "library-RTL.css",
			"size": 73702,
			"theme": "sap_fiori_3_hcb"
		},
		{
			"name": "library-parameters.json",
			"size": 216,
			"theme": "sap_fiori_3_hcb"
		},
		{
			"name": "library.css",
			"size": 73697,
			"theme": "sap_fiori_3_hcb"
		},
		{
			"name": "library.less",
			"size": 25073,
			"designtime": true,
			"theme": "sap_fiori_3_hcb"
		},
		{
			"name": "library.source.less",
			"size": 622,
			"designtime": true,
			"theme": "sap_fiori_3_hcb"
		},
		{
			"name": "library_skeleton-RTL.css",
			"size": 76071,
			"theme": "sap_fiori_3_hcb"
		},
		{
			"name": "library_skeleton.css",
			"size": 76066,
			"theme": "sap_fiori_3_hcb"
		}
	]
}